{"labels": ["Doing_other_things", "Drumming_Fingers", "No_gesture", "Pulling_Hand_In", "Pulling_Two_Fingers_In", "Pushing_Hand_Away", "Pushing_Two_Fingers_Away", "Rolling_Hand_Backward", "Rolling_Hand_Forward", "Shaking_Hand", "Sliding_Two_Fingers_Down", "Sliding_Two_Fingers_Left", "Sliding_Two_Fingers_Right", "Sliding_Two_Fingers_Up", "Stop_Sign", "Swiping_Down", "Swiping_Left", "Swiping_Right", "Swiping_Up", "Thumb_Down", "Thumb_Up", "Turning_Hand_Clockwise", "Turning_Hand_Counterclockwise", "Zooming_In_With_Full_Hand", "Zooming_In_With_Two_Fingers", "Zooming_Out_With_Full_Hand", "Zooming_Out_With_Two_Fingers"], "database": {"34870": {"subset": "training", "annotations": {"label": "Drumming_Fingers"}}, "56557": {"subset": "training", "annotations": {"label": "Sliding_Two_Fingers_Right"}}, "129112": {"subset": "training", "annotations": {"label": "Sliding_Two_Fingers_Down"}}, "63861": {"subset": "training", "annotations": {"label": "Pulling_Two_Fingers_In"}}, "131717": {"subset": "training", "annotations": {"label": "Sliding_Two_Fingers_Up"}}, "23595": {"subset": "training", "annotations": {"label": "Zooming_Out_With_Two_Fingers"}}, "93002": {"subset": "training", "annotations": {"label": "Pulling_Hand_In"}}, "136859": {"subset": "training", "annotations": {"label": "Thumb_Up"}}, "68574": {"subset": "training", "annotations": {"label": "Swiping_Right"}}, "119263": {"subset": "training", "annotations": {"label": "Zooming_In_With_Two_Fingers"}}, "60572": {"subset": "training", "annotations": {"label": "Stop_Sign"}}, "118480": {"subset": "training", "annotations": {"label": "Doing_other_things"}}, "6522": {"subset": "training", "annotations": {"label": "Swiping_Down"}}, "20706": {"subset": "training", "annotations": {"label": "No_gesture"}}, "42237": {"subset": "training", "annotations": {"label": "Thumb_Down"}}, "142698": {"subset": "training", "annotations": {"label": "Pulling_Hand_In"}}, "9223": {"subset": "validation", "annotations": {"label": "Thumb_Up"}}, "107090": {"subset": "validation", "annotations": {"label": "Pushing_Two_Fingers_Away"}}, "42920": {"subset": "validation", "annotations": {"label": "Swiping_Left"}}, "106485": {"subset": "validation", "annotations": {"label": "Thumb_Down"}}, "142201": {"subset": "validation", "annotations": {"label": "Rolling_Hand_Backward"}}, "12912": {"subset": "validation", "annotations": {"label": "Sliding_Two_Fingers_Right"}}, "148031": {"subset": "testing", "annotations": {"label": "Doing_other_things"}}, "148050": {"subset": "testing", "annotations": {"label": "Doing_other_things"}}, "148063": {"subset": "testing", "annotations": {"label": "Doing_other_things"}}, "148068": {"subset": "testing", "annotations": {"label": "Doing_other_things"}}, "148073": {"subset": "testing", "annotations": {"label": "Doing_other_things"}}, "148087": {"subset": "testing", "annotations": {"label": "Doing_other_things"}}}}